[{"type":"tab","id":"f1243742.5df718","label":"test"},{"id":"849c4b7.6ccb8b8","type":"twitter","z":"f1243742.5df718","name":"last_tweet","subtype":"twitterHashTagStream","x":124,"y":225,"wires":[["6821de9.5f8c52"]]},{"id":"6821de9.5f8c52","type":"function","z":"f1243742.5df718","name":"find out ","func":"if (msg.payload.value.match(/thank/i))\n    msg.payload.value=\"YYYY:\".concat(msg.payload.value)\nelse\n    msg.payload.value=\"NNNN:\".concat(msg.payload.value)\nreturn msg","outputs":1,"noerr":0,"x":212,"y":128,"wires":[["c61bfcd3.41cd6","5c5c7a5e.d93254","39bfb70b.54f258","988dbd40.94eda","b0b13971.df8178"]]},{"id":"c61bfcd3.41cd6","type":"notify","z":"f1243742.5df718","name":"email","subtype":"twitter","message":"","to":"sz41@st-andrews.ac.uk","x":229,"y":467,"wires":[]},{"id":"5c5c7a5e.d93254","type":"bulbsout","z":"f1243742.5df718","name":"turn it on","subtype":"set-bulb-on","value":"false","x":417,"y":228,"wires":[]},{"id":"39bfb70b.54f258","type":"app","z":"f1243742.5df718","name":"","appId":"webapp","layout":null,"x":393,"y":323,"wires":[]},{"id":"988dbd40.94eda","type":"pipstaprint","z":"f1243742.5df718","name":"","message":"","subtype":"printer","x":306,"y":421,"wires":[]},{"id":"b0b13971.df8178","type":"debugger","z":"f1243742.5df718","name":"","active":true,"console":"false","complete":"false","x":425,"y":121,"wires":[]}]